blynkapi
