Metadata-Version: 1.1
Name: blynkapi
Version: 0.1.7
Summary: This is a simple blynk HTTP/HTTPS API wrapper.
Home-page: https://github.com/xandr2/blynkapi
Author: Alexandr Borysov
Author-email: xandr2@gmail.com
License: MIT
Download-URL: https://github.com/xandr2/blynkapi/archive/0.1.7.tar.gz
Keywords: python,blynk,HTTP/HTTPS,API,wrapper
Platform: UNKNOWN
